<?xml version="1.0"?>
<Tree x="21" y="1" type="0" />
<Tree x="5" y="2" type="1" />
<Tree x="4" y="4" type="0" />
<Tree x="5" y="5" type="0" />
<Tree x="17" y="7" type="1" />
<Tree x="13" y="8" type="0" />
<Tree x="22" y="12" type="0" />
<Tree x="8" y="13" type="1" />
<Tree x="12" y="15" type="0" />
<Tree x="15" y="7" type="0" />
<Tree x="20" y="3" type="1" />
<Tree x="30" y="5" type="0" />
<Tree x="24" y="8" type="0" />
<Tree x="25" y="9" type="1" />
<Tree x="32" y="15" type="0" />
<Tree x="28" y="7" type="0" />
<Inventory ingot="50" iron="1000" stone="1000" coal="1000" wood="1000" pollution="0" />